{"duration":2027,"records":[{"duration":840,"stepId":"io.quarkus.vertx.http.deployment.devmode.console.DevConsoleProcessor#setupDeploymentSideHandling","started":"20:24:27.020","dependents":[349,350,348],"id":347,"thread":"build-11"},{"duration":534,"stepId":"io.quarkus.vertx.http.deployment.webjar.WebJarProcessor#processWebJarDevMode","started":"20:24:26.067","dependents":[353,278,324],"id":277,"thread":"build-20"},{"duration":462,"stepId":"io.quarkus.hibernate.orm.deployment.HibernateOrmProcessor#enhancerDomainObjects","started":"20:24:26.813","dependents":[343,344,345],"id":342,"thread":"build-49"},{"duration":346,"stepId":"io.quarkus.deployment.console.ConsoleProcessor#setupConsole","started":"20:24:26.056","dependents":[221,302,215,216],"id":214,"thread":"build-17"},{"duration":291,"stepId":"io.quarkus.datasource.deployment.devservices.DevUIDatasourceProcessor#devConsoleCleanDatabaseHandler","started":"20:24:25.984","dependents":[353,347,324],"id":187,"thread":"build-11"},{"duration":272,"stepId":"io.quarkus.vertx.core.deployment.VertxCoreProcessor#createVertxThreadFactory","started":"20:24:25.995","dependents":[353,202],"id":176,"thread":"build-25"},{"duration":270,"stepId":"io.quarkus.deployment.logging.LoggingResourceProcessor#logConsoleCommand","started":"20:24:26.018","dependents":[308],"id":195,"thread":"build-4"},{"duration":269,"stepId":"io.quarkus.datasource.deployment.devservices.DevServicesDatasourceProcessor#launchDatabases","started":"20:24:26.580","dependents":[303,305],"id":302,"thread":"build-12"},{"duration":268,"stepId":"io.quarkus.deployment.ide.IdeProcessor#detectRunningIdeProcesses","started":"20:24:25.975","dependents":[162],"id":161,"thread":"build-1"},{"duration":267,"stepId":"io.quarkus.vertx.http.deployment.devmode.ArcDevProcessor#eventsEndpoint","started":"20:24:26.003","dependents":[353,347,324],"id":182,"thread":"build-19"},{"duration":263,"stepId":"io.quarkus.vertx.core.deployment.VertxCoreProcessor#ioThreadDetector","started":"20:24:26.026","dependents":[353,200],"id":196,"thread":"build-3"},{"duration":261,"stepId":"io.quarkus.mutiny.deployment.MutinyProcessor#buildTimeInit","started":"20:24:25.996","dependents":[353],"id":167,"thread":"build-26"},{"duration":248,"stepId":"io.quarkus.vertx.core.deployment.VertxCoreProcessor#createVertxContextHandlers","started":"20:24:26.037","dependents":[353,202,203],"id":193,"thread":"build-24"},{"duration":247,"stepId":"io.quarkus.deployment.steps.ConfigDescriptionBuildStep#createConfigDescriptions","started":"20:24:26.055","dependents":[347,307],"id":201,"thread":"build-5"},{"duration":235,"stepId":"io.quarkus.deployment.dev.io.NioThreadPoolDevModeProcessor#setupTCCL","started":"20:24:26.032","dependents":[353],"id":177,"thread":"build-12"},{"duration":235,"stepId":"io.quarkus.vertx.http.deployment.devmode.ArcDevProcessor#invocationsEndpoint","started":"20:24:26.032","dependents":[353,347,324],"id":178,"thread":"build-41"},{"duration":224,"stepId":"io.quarkus.deployment.steps.PreloadClassesBuildStep#preInit","started":"20:24:26.030","dependents":[353],"id":165,"thread":"build-43"},{"duration":220,"stepId":"io.quarkus.deployment.steps.ApplicationIndexBuildStep#build","started":"20:24:26.064","dependents":[290,217,284,194],"id":191,"thread":"build-56"},{"duration":220,"stepId":"io.quarkus.netty.deployment.NettyProcessor#eagerlyInitClass","started":"20:24:26.035","dependents":[353],"id":166,"thread":"build-48"},{"duration":219,"stepId":"io.quarkus.vertx.deployment.VertxProcessor#currentContextFactory","started":"20:24:26.060","dependents":[353,325],"id":189,"thread":"build-49"},{"duration":219,"stepId":"io.quarkus.vertx.http.deployment.devmode.console.DevConsoleProcessor#handler","started":"20:24:26.056","dependents":[353,276,324],"id":185,"thread":"build-55"},{"duration":216,"stepId":"io.quarkus.resteasy.deployment.ResteasyStandaloneBuildStep#addDefaultAuthFailureHandler","started":"20:24:26.059","dependents":[353,339],"id":186,"thread":"build-65"},{"duration":211,"stepId":"io.quarkus.narayana.jta.deployment.NarayanaJtaProcessor#build","started":"20:24:26.183","dependents":[353,352,284,269,212],"id":211,"thread":"build-57"},{"duration":208,"stepId":"io.quarkus.smallrye.context.deployment.SmallRyeContextPropagationProcessor#buildStatic","started":"20:24:26.083","dependents":[353],"id":198,"thread":"build-51"},{"duration":203,"stepId":"io.quarkus.hibernate.orm.deployment.HibernateOrmProcessor#parsePersistenceXmlDescriptors","started":"20:24:26.030","dependents":[157,213,255],"id":156,"thread":"build-37"},{"duration":203,"stepId":"io.quarkus.deployment.logging.LoggingResourceProcessor#setupLoggingStaticInit","started":"20:24:26.055","dependents":[353],"id":168,"thread":"build-13"},{"duration":203,"stepId":"io.quarkus.deployment.steps.ConfigGenerationBuildStep#watchConfigFiles","started":"20:24:26.032","dependents":[268],"id":158,"thread":"build-32"},{"duration":203,"stepId":"io.quarkus.arc.deployment.devconsole.ArcDevConsoleProcessor#exposeArcContainer","started":"20:24:26.064","dependents":[353,349],"id":174,"thread":"build-15"},{"duration":203,"stepId":"io.quarkus.netty.deployment.NettyProcessor#setNettyMachineId","started":"20:24:26.037","dependents":[353],"id":160,"thread":"build-40"},{"duration":202,"stepId":"io.quarkus.datasource.deployment.DataSourcesExcludedFromHealthChecksProcessor#produceBean","started":"20:24:26.070","dependents":[353,299,296,298],"id":183,"thread":"build-53"},{"duration":199,"stepId":"io.quarkus.resteasy.deployment.ResteasyBuiltinsProcessor#addReactiveRoutesExceptionMapper","started":"20:24:26.073","dependents":[353],"id":184,"thread":"build-2"},{"duration":197,"stepId":"io.quarkus.deployment.logging.LoggingResourceProcessor#registerMetrics","started":"20:24:26.055","dependents":[353,276],"id":164,"thread":"build-61"},{"duration":194,"stepId":"io.quarkus.resteasy.deployment.ResteasyBuiltinsProcessor#setupExceptionMapper","started":"20:24:26.073","dependents":[353,279],"id":171,"thread":"build-9"},{"duration":179,"stepId":"io.quarkus.deployment.index.ApplicationArchiveBuildStep#build","started":"20:24:26.284","dependents":[221,220,269,218,249,333,237,222,314,255,246,343,345],"id":217,"thread":"build-38"},{"duration":178,"stepId":"io.quarkus.vertx.http.deployment.devmode.tests.TestsProcessor#setupTestRoutes","started":"20:24:26.098","dependents":[353,347,338,336,216],"id":188,"thread":"build-28"},{"duration":172,"stepId":"io.quarkus.deployment.steps.ConfigGenerationBuildStep#generateConfigClass","started":"20:24:26.876","dependents":[352],"id":341,"thread":"build-56"},{"duration":164,"stepId":"io.quarkus.hibernate.orm.deployment.HibernateOrmCdiProcessor#registerAnnotations","started":"20:24:25.978","dependents":[144,284,269],"id":142,"thread":"build-6"},{"duration":163,"stepId":"io.quarkus.agroal.deployment.AgroalProcessor#build","started":"20:24:26.073","dependents":[352,169,170,199,212,264],"id":159,"thread":"build-35"},{"duration":162,"stepId":"io.quarkus.deployment.steps.BootstrapConfigSetupBuildStep#setupBootstrapConfig","started":"20:24:26.020","dependents":[353,151],"id":150,"thread":"build-18"},{"duration":157,"stepId":"io.quarkus.deployment.steps.ConfigGenerationBuildStep#setupConfigOverride","started":"20:24:26.021","dependents":[],"id":148,"thread":"build-38"},{"duration":157,"stepId":"io.quarkus.vertx.http.deployment.devmode.console.DevConsoleProcessor#collectTemplates","started":"20:24:26.047","dependents":[347],"id":155,"thread":"build-58"},{"duration":153,"stepId":"io.quarkus.deployment.console.ConsoleProcessor#helpCommand","started":"20:24:26.020","dependents":[308],"id":146,"thread":"build-10"},{"duration":149,"stepId":"io.quarkus.vertx.http.deployment.HttpSecurityProcessor#setupAuthenticationMechanisms","started":"20:24:26.118","dependents":[353,339,325,284,269],"id":175,"thread":"build-39"},{"duration":145,"stepId":"io.quarkus.arc.deployment.ArcProcessor#registerBeans","started":"20:24:26.664","dependents":[295,288,287,300,293,299,292,290,296,291,298,294,289],"id":286,"thread":"build-28"},{"duration":143,"stepId":"io.quarkus.deployment.steps.ConfigGenerationBuildStep#buildTimeRunTimeConfig","started":"20:24:26.055","dependents":[352,341],"id":154,"thread":"build-33"},{"duration":142,"stepId":"io.quarkus.vertx.http.deployment.VertxHttpProcessor#bodyHandler","started":"20:24:26.183","dependents":[353,339,324],"id":209,"thread":"build-6"},{"duration":138,"stepId":"io.quarkus.deployment.console.ConsoleProcessor#quitCommand","started":"20:24:26.037","dependents":[308],"id":147,"thread":"build-50"},{"duration":136,"stepId":"io.quarkus.deployment.logging.LoggingResourceProcessor#setMinLevelForInitialConfigurator","started":"20:24:26.054","dependents":[353],"id":153,"thread":"build-31"},{"duration":134,"stepId":"io.quarkus.deployment.steps.BannerProcessor#recordBanner","started":"20:24:26.183","dependents":[353,276],"id":206,"thread":"build-30"},{"duration":131,"stepId":"io.quarkus.arc.deployment.ArcProcessor#generateResources","started":"20:24:26.883","dependents":[353,326,352,345],"id":325,"thread":"build-11"},{"duration":128,"stepId":"io.quarkus.deployment.steps.MainClassBuildStep#build","started":"20:24:27.861","dependents":[],"id":353,"thread":"build-56"},{"duration":126,"stepId":"io.quarkus.vertx.deployment.VertxProcessor#autoAddScope","started":"20:24:25.987","dependents":[275],"id":136,"thread":"build-14"},{"duration":115,"stepId":"io.quarkus.deployment.steps.ConfigBuildSteps#generateConfigSources","started":"20:24:26.064","dependents":[],"id":149,"thread":"build-62"},{"duration":111,"stepId":"io.quarkus.arc.deployment.ArcProcessor#quarkusMain","started":"20:24:26.032","dependents":[144,284,269],"id":143,"thread":"build-44"},{"duration":106,"stepId":"io.quarkus.deployment.logging.LoggingResourceProcessor#setupLoggingRuntimeInit","started":"20:24:26.473","dependents":[353,352,347,302,340,324],"id":276,"thread":"build-11"},{"duration":101,"stepId":"io.quarkus.vertx.http.deployment.HttpSecurityProcessor#initBasicAuth","started":"20:24:26.183","dependents":[353,299,296,298],"id":190,"thread":"build-38"},{"duration":101,"stepId":"io.quarkus.vertx.core.deployment.VertxCoreProcessor#eventLoopCount","started":"20:24:26.183","dependents":[353,351],"id":192,"thread":"build-44"},{"duration":88,"stepId":"io.quarkus.arc.deployment.CommandLineArgumentsProcessor#commandLineArgs","started":"20:24:26.041","dependents":[299,296,284,269,298],"id":141,"thread":"build-54"},{"duration":86,"stepId":"io.quarkus.hibernate.orm.deployment.HibernateOrmProcessor#setupPersistenceProvider","started":"20:24:26.183","dependents":[353,197,328],"id":181,"thread":"build-45"},{"duration":85,"stepId":"io.quarkus.vertx.http.deployment.devmode.console.DevConsoleProcessor#setupConsole","started":"20:24:26.098","dependents":[349,350,348],"id":152,"thread":"build-52"},{"duration":85,"stepId":"io.quarkus.deployment.steps.ConfigGenerationBuildStep#checkForBuildTimeConfigChange","started":"20:24:26.183","dependents":[353],"id":180,"thread":"build-50"},{"duration":84,"stepId":"io.quarkus.vertx.http.deployment.HttpSecurityProcessor#initMtlsClientAuth","started":"20:24:26.183","dependents":[353,299,296,298],"id":173,"thread":"build-10"},{"duration":84,"stepId":"io.quarkus.vertx.http.deployment.VertxHttpProcessor#cors","started":"20:24:26.183","dependents":[353,339],"id":179,"thread":"build-18"},{"duration":84,"stepId":"io.quarkus.vertx.http.deployment.HttpSecurityProcessor#initFormAuth","started":"20:24:26.183","dependents":[353,299,347,338,296,336,298],"id":172,"thread":"build-54"},{"duration":70,"stepId":"io.quarkus.deployment.logging.LoggingResourceProcessor#setUpDefaultLogCleanupFilters","started":"20:24:26.083","dependents":[319],"id":145,"thread":"build-45"},{"duration":66,"stepId":"io.quarkus.vertx.deployment.VertxProcessor#unremovableBeans","started":"20:24:26.036","dependents":[313,309],"id":133,"thread":"build-47"},{"duration":64,"stepId":"io.quarkus.resteasy.common.deployment.ResteasyCommonProcessor#setupProviders","started":"20:24:26.559","dependents":[352,313,309,280],"id":279,"thread":"build-28"},{"duration":64,"stepId":"io.quarkus.vertx.http.deployment.VertxHttpProcessor#logging","started":"20:24:25.989","dependents":[107],"id":72,"thread":"build-17"},{"duration":62,"stepId":"io.quarkus.arc.deployment.ConfigBuildStep#registerConfigRootsAsBeans","started":"20:24:26.060","dependents":[299,296,298],"id":140,"thread":"build-57"},{"duration":60,"stepId":"io.quarkus.resteasy.deployment.ResteasyBuiltinsProcessor#vertxProviders","started":"20:24:26.037","dependents":[279],"id":129,"thread":"build-28"},{"duration":59,"stepId":"io.quarkus.jdbc.h2.deployment.JDBCH2Processor#registerDefaultDbType","started":"20:24:26.014","dependents":[302,159],"id":121,"thread":"build-9"},{"duration":58,"stepId":"io.quarkus.vertx.http.deployment.HttpSecurityProcessor#builtins","started":"20:24:26.060","dependents":[284,175,269],"id":139,"thread":"build-30"},{"duration":56,"stepId":"io.quarkus.agroal.deployment.AgroalProcessor#generateDataSourceSupportBean","started":"20:24:26.237","dependents":[353,299,296,284,269,298,313,309],"id":199,"thread":"build-37"},{"duration":54,"stepId":"io.quarkus.deployment.steps.ClassTransformingBuildStep#handleClassTransformation","started":"20:24:27.279","dependents":[346],"id":345,"thread":"build-56"},{"duration":50,"stepId":"io.quarkus.hibernate.orm.deployment.HibernateOrmProcessor#handleMoveSql","started":"20:24:26.064","dependents":[349],"id":138,"thread":"build-39"},{"duration":49,"stepId":"io.quarkus.vertx.core.deployment.VertxCoreProcessor#doNotRemoveVertxOptionsCustomizers","started":"20:24:25.993","dependents":[313,309],"id":51,"thread":"build-21"},{"duration":48,"stepId":"io.quarkus.vertx.http.deployment.devmode.tests.TestsProcessor#toggleTestRunner","started":"20:24:26.021","dependents":[347,324],"id":113,"thread":"build-23"},{"duration":46,"stepId":"io.quarkus.netty.deployment.NettyProcessor#registerQualifiers","started":"20:24:25.988","dependents":[284,269],"id":31,"thread":"build-15"},{"duration":46,"stepId":"io.quarkus.devservices.h2.deployment.H2DevServicesProcessor#setupH2","started":"20:24:25.987","dependents":[302],"id":29,"thread":"build-12"},{"duration":46,"stepId":"io.quarkus.arc.deployment.StartupBuildSteps#addScope","started":"20:24:26.053","dependents":[275],"id":131,"thread":"build-22"},{"duration":45,"stepId":"io.quarkus.jdbc.h2.deployment.JDBCH2Processor#devDbHandler","started":"20:24:25.997","dependents":[302],"id":57,"thread":"build-27"},{"duration":45,"stepId":"io.quarkus.deployment.pkg.steps.JarResultBuildStep#outputTarget","started":"20:24:26.054","dependents":[134],"id":132,"thread":"build-8"},{"duration":45,"stepId":"io.quarkus.vertx.http.deployment.devmode.tests.TestsProcessor#toggleTestOutput","started":"20:24:26.018","dependents":[347,324],"id":106,"thread":"build-29"},{"duration":45,"stepId":"io.quarkus.vertx.http.deployment.devmode.tests.TestsProcessor#toggleLiveReloadEnabled","started":"20:24:26.018","dependents":[347,324],"id":99,"thread":"build-35"},{"duration":44,"stepId":"io.quarkus.hibernate.orm.deployment.devconsole.HibernateDevConsoleProcessor#collectDeploymentUnits","started":"20:24:26.067","dependents":[349],"id":135,"thread":"build-36"},{"duration":44,"stepId":"io.quarkus.arc.deployment.BeanArchiveProcessor#build","started":"20:24:26.515","dependents":[284,270,295,272,274,275,294,271,279,280],"id":269,"thread":"build-5"},{"duration":44,"stepId":"io.quarkus.resteasy.deployment.ResteasyBuiltinsProcessor#setUpSecurity","started":"20:24:26.070","dependents":[284,269,279],"id":137,"thread":"build-42"},{"duration":43,"stepId":"io.quarkus.vertx.http.deployment.devmode.tests.TestsProcessor#runFailedTests","started":"20:24:26.019","dependents":[347,324],"id":102,"thread":"build-20"},{"duration":42,"stepId":"io.quarkus.vertx.http.deployment.devmode.tests.TestsProcessor#printfailures","started":"20:24:26.021","dependents":[347,324],"id":104,"thread":"build-39"},{"duration":41,"stepId":"io.quarkus.vertx.http.deployment.VertxHttpProcessor#filterMultipleVertxInstancesWarning","started":"20:24:26.041","dependents":[145,276],"id":126,"thread":"build-51"},{"duration":41,"stepId":"io.quarkus.deployment.DockerStatusProcessor#IsDockerWorking","started":"20:24:26.033","dependents":[302,305],"id":125,"thread":"build-45"},{"duration":39,"stepId":"io.quarkus.vertx.http.deployment.VertxHttpProcessor#hostDefault","started":"20:24:26.025","dependents":[149],"id":108,"thread":"build-7"},{"duration":38,"stepId":"io.quarkus.vertx.http.deployment.VertxHttpProcessor#frameworkRoot","started":"20:24:26.059","dependents":[339,347,338,188,321,278,324,152],"id":130,"thread":"build-66"},{"duration":37,"stepId":"io.quarkus.narayana.jta.deployment.NarayanaJtaProcessor#unremovableBean","started":"20:24:26.016","dependents":[313,309],"id":74,"thread":"build-33"},{"duration":36,"stepId":"io.quarkus.hibernate.orm.deployment.HibernateOrmProcessor#defineJpaEntities","started":"20:24:26.477","dependents":[261,352,254,268,263,346,258,257,259,342,255,328],"id":253,"thread":"build-57"},{"duration":36,"stepId":"io.quarkus.arc.deployment.ArcProcessor#validate","started":"20:24:26.836","dependents":[310,325,316,315,321,318,322,312,313,314,345,311],"id":309,"thread":"build-20"},{"duration":35,"stepId":"io.quarkus.arc.deployment.ArcProcessor#unremovableAsyncObserverExceptionHandlers","started":"20:24:26.001","dependents":[313,309],"id":37,"thread":"build-30"},{"duration":35,"stepId":"io.quarkus.vertx.core.deployment.VertxCoreProcessor#overrideContextInternalInterfaceToAddSafeGuards","started":"20:24:25.998","dependents":[345],"id":30,"thread":"build-28"},{"duration":34,"stepId":"io.quarkus.deployment.ide.IdeProcessor#detectIdeFiles","started":"20:24:26.018","dependents":[162],"id":67,"thread":"build-13"},{"duration":33,"stepId":"io.quarkus.vertx.http.deployment.devmode.tests.TestsProcessor#runAllTests","started":"20:24:26.030","dependents":[347,324],"id":97,"thread":"build-2"},{"duration":30,"stepId":"io.quarkus.vertx.http.deployment.devmode.tests.TestsProcessor#results","started":"20:24:26.032","dependents":[323],"id":96,"thread":"build-16"},{"duration":30,"stepId":"io.quarkus.deployment.steps.NativeImageConfigBuildStep#build","started":"20:24:26.237","dependents":[353],"id":170,"thread":"build-58"},{"duration":28,"stepId":"io.quarkus.vertx.http.deployment.devmode.BuildMetricsDevConsoleProcessor#collectMetrics","started":"20:24:26.035","dependents":[323],"id":103,"thread":"build-15"},{"duration":27,"stepId":"io.quarkus.arc.deployment.UnremovableAnnotationsProcessor#unremovableBeans","started":"20:24:26.002","dependents":[313,309],"id":25,"thread":"build-32"},{"duration":27,"stepId":"io.quarkus.deployment.dev.testing.TestTracingProcessor#sharedStateListener","started":"20:24:26.003","dependents":[216],"id":24,"thread":"build-24"},{"duration":27,"stepId":"io.quarkus.arc.deployment.ArcProcessor#registerContextPropagation","started":"20:24:26.055","dependents":[198],"id":127,"thread":"build-46"},{"duration":26,"stepId":"io.quarkus.agroal.deployment.AgroalMetricsProcessor#registerMetrics","started":"20:24:26.237","dependents":[353],"id":169,"thread":"build-32"},{"duration":26,"stepId":"io.quarkus.arc.deployment.ArcProcessor#initialize","started":"20:24:26.635","dependents":[286,322,285],"id":284,"thread":"build-28"},{"duration":23,"stepId":"io.quarkus.jdbc.h2.deployment.JDBCH2Processor#configureAgroalConnection","started":"20:24:26.070","dependents":[284,269],"id":128,"thread":"build-52"},{"duration":23,"stepId":"io.quarkus.arc.deployment.devconsole.ArcDevConsoleProcessor#collectBeanInfo","started":"20:24:26.872","dependents":[347,323,324],"id":322,"thread":"build-57"},{"duration":22,"stepId":"io.quarkus.vertx.http.deployment.devmode.console.DevConsoleProcessor#setupDevConsoleRoutes_0a9629c46f632dba90d4b3c7602ae4ea9d736452","started":"20:24:26.896","dependents":[353,347,338,336],"id":324,"thread":"build-5"},{"duration":22,"stepId":"io.quarkus.arc.deployment.LoggingBeanSupportProcessor#discoveredComponents","started":"20:24:26.037","dependents":[144,284,269],"id":89,"thread":"build-30"},{"duration":21,"stepId":"io.quarkus.vertx.http.deployment.VertxHttpProcessor#additionalBeans","started":"20:24:26.021","dependents":[284,269],"id":56,"thread":"build-36"},{"duration":21,"stepId":"io.quarkus.vertx.http.deployment.devmode.tests.TestsProcessor#handleTestResult","started":"20:24:26.042","dependents":[347,324],"id":98,"thread":"build-42"},{"duration":21,"stepId":"io.quarkus.deployment.steps.ThreadPoolSetup#createExecutor","started":"20:24:26.285","dependents":[353,339,205,203,204,207,335],"id":202,"thread":"build-56"},{"duration":20,"stepId":"io.quarkus.hibernate.orm.deployment.metrics.HibernateOrmMetricsProcessor#metrics","started":"20:24:26.269","dependents":[353],"id":197,"thread":"build-50"},{"duration":19,"stepId":"io.quarkus.arc.deployment.ArcProcessor#convertLegacyAdditionalStereotypes","started":"20:24:26.022","dependents":[284,272],"id":46,"thread":"build-31"},{"duration":18,"stepId":"io.quarkus.smallrye.context.deployment.SmallRyeContextPropagationProcessor#registerBean","started":"20:24:26.002","dependents":[284,269],"id":19,"thread":"build-31"},{"duration":18,"stepId":"io.quarkus.deployment.steps.DevModeBuildStep#watchChanges","started":"20:24:26.055","dependents":[268],"id":124,"thread":"build-60"},{"duration":17,"stepId":"io.quarkus.vertx.core.deployment.VertxCoreProcessor#build_9d6b7122fb368970c50c3a870d1f672392cd8afb","started":"20:24:26.042","dependents":[352,170,264],"id":91,"thread":"build-57"},{"duration":17,"stepId":"io.quarkus.netty.deployment.NettyProcessor#cleanupUnsafeLog","started":"20:24:26.020","dependents":[145,276],"id":41,"thread":"build-22"},{"duration":16,"stepId":"io.quarkus.smallrye.context.deployment.SmallRyeContextPropagationProcessor#transformInjectionPoint","started":"20:24:25.975","dependents":[284],"id":10,"thread":"build-3"},{"duration":16,"stepId":"io.quarkus.vertx.http.deployment.devmode.console.ConfigEditorProcessor#config","started":"20:24:26.853","dependents":[353,347,349,308,324],"id":307,"thread":"build-6"},{"duration":16,"stepId":"io.quarkus.vertx.http.deployment.devmode.tests.TestsProcessor#forceRestart","started":"20:24:26.047","dependents":[347,324],"id":105,"thread":"build-56"},{"duration":16,"stepId":"io.quarkus.vertx.http.deployment.devmode.tests.TestsProcessor#handleTestStatus","started":"20:24:26.047","dependents":[347,324],"id":100,"thread":"build-27"},{"duration":15,"stepId":"io.quarkus.resteasy.deployment.ResteasyBuiltinsProcessor#addStaticResourcesExceptionMapper","started":"20:24:26.464","dependents":[353],"id":249,"thread":"build-6"},{"duration":15,"stepId":"io.quarkus.vertx.http.deployment.devmode.tests.TestsProcessor#toggleInstrumentation","started":"20:24:26.047","dependents":[347,324],"id":95,"thread":"build-59"},{"duration":15,"stepId":"io.quarkus.arc.deployment.ArcProcessor#launchMode","started":"20:24:26.039","dependents":[284,269],"id":76,"thread":"build-52"},{"duration":15,"stepId":"io.quarkus.deployment.dev.IsolatedDevModeMain$5$1@382e2e05","started":"20:24:26.022","dependents":[284],"id":42,"thread":"build-5"},{"duration":14,"stepId":"io.quarkus.vertx.http.deployment.VertxHttpProcessor#preinitializeRouter","started":"20:24:26.319","dependents":[353,299,338,296,298],"id":210,"thread":"build-5"},{"duration":14,"stepId":"io.quarkus.arc.deployment.ArcProcessor#marker","started":"20:24:26.003","dependents":[217],"id":18,"thread":"build-20"},{"duration":14,"stepId":"io.quarkus.deployment.pkg.steps.PackageTypeVerificationBuildStep#verify","started":"20:24:26.054","dependents":[349,350,348],"id":112,"thread":"build-52"},{"duration":14,"stepId":"io.quarkus.deployment.dev.testing.TestTracingProcessor#testConsoleCommand","started":"20:24:26.473","dependents":[308],"id":252,"thread":"build-49"},{"duration":13,"stepId":"io.quarkus.arc.deployment.ConfigBuildStep#additionalBeans","started":"20:24:26.040","dependents":[284,269],"id":77,"thread":"build-5"},{"duration":13,"stepId":"io.quarkus.vertx.http.deployment.VertxHttpProcessor#httpRoot","started":"20:24:26.060","dependents":[339,337,333,171,281,184,152],"id":122,"thread":"build-64"},{"duration":13,"stepId":"io.quarkus.arc.deployment.SyntheticBeansProcessor#initRegular","started":"20:24:26.811","dependents":[300],"id":299,"thread":"build-45"},{"duration":12,"stepId":"io.quarkus.credentials.CredentialsProcessor#unremoveable","started":"20:24:26.037","dependents":[313,309],"id":64,"thread":"build-49"},{"duration":12,"stepId":"io.quarkus.deployment.ExtensionLoader#config","started":"20:24:26.040","dependents":[179,80,272,207,144,290,284,209,255,211,324,302,120,350,269,191,276,153,231,351,353,197,247,78,112,192,84,214,279,132,159,173,81,83,168,181,169,82,257,183,110,127,85,154,216,201,164,210,340,332,333,124,92,232,94,90,172,206,202,175,88,258,185,319,186,86,130,313,101,345,220,325,338,109,317,180,335,280,310,123,273,321,162,234,246,277,212,348,330,122,341,138,267,339,115,189,190,217,139,93,140],"id":75,"thread":"build-34"},{"duration":12,"stepId":"io.quarkus.hibernate.orm.deployment.HibernateOrmProcessor#contributeQuarkusConfigToJpaModel","started":"20:24:26.061","dependents":[253],"id":123,"thread":"build-67"},{"duration":12,"stepId":"io.quarkus.jackson.deployment.JacksonProcessor#generateCustomizer","started":"20:24:26.474","dependents":[269],"id":251,"thread":"build-12"},{"duration":12,"stepId":"io.quarkus.jackson.deployment.JacksonProcessor#unremovable","started":"20:24:26.473","dependents":[313,309],"id":250,"thread":"build-18"},{"duration":12,"stepId":"io.quarkus.vertx.http.deployment.VertxHttpProcessor#shouldNotRemoveHttpServerOptionsCustomizers","started":"20:24:26.042","dependents":[313,309],"id":79,"thread":"build-53"},{"duration":11,"stepId":"io.quarkus.deployment.dev.HotDeploymentWatchedFileBuildStep#setupWatchedFileHotDeployment","started":"20:24:26.515","dependents":[349,350,348],"id":268,"thread":"build-49"},{"duration":11,"stepId":"io.quarkus.deployment.steps.ProfileBuildStep#defaultProfile","started":"20:24:26.040","dependents":[319],"id":68,"thread":"build-22"},{"duration":11,"stepId":"io.quarkus.vertx.core.deployment.VertxCoreProcessor#build_9fb3ce360263cc99d07c9172ec2feeaa85afcc1a","started":"20:24:26.307","dependents":[297,349,338,350,351,208,335,299,210,353,339,296,332,298,348],"id":207,"thread":"build-51"},{"duration":11,"stepId":"io.quarkus.resteasy.server.common.deployment.ResteasyServerCommonProcessor#build","started":"20:24:26.623","dependents":[352,333,284,331,281,283,313,345,309],"id":280,"thread":"build-11"},{"duration":11,"stepId":"io.quarkus.vertx.http.deployment.StaticResourcesProcessor#collectStaticResources","started":"20:24:26.464","dependents":[332],"id":237,"thread":"build-30"},{"duration":11,"stepId":"io.quarkus.arc.deployment.ArcProcessor#transformListAllInjectionPoints","started":"20:24:26.030","dependents":[284],"id":48,"thread":"build-42"},{"duration":10,"stepId":"io.quarkus.vertx.http.deployment.devmode.ArcDevProcessor#registerRoutes","started":"20:24:26.872","dependents":[353,347,337,338,325,336],"id":321,"thread":"build-45"},{"duration":10,"stepId":"io.quarkus.deployment.recording.substitutions.AdditionalSubstitutionsBuildStep#additionalSubstitutions","started":"20:24:26.042","dependents":[353],"id":71,"thread":"build-55"},{"duration":10,"stepId":"io.quarkus.arc.deployment.SyntheticBeansProcessor#initRuntime","started":"20:24:26.811","dependents":[353,349,350,300,328,348],"id":298,"thread":"build-20"},{"duration":10,"stepId":"io.quarkus.deployment.steps.DevServicesConfigBuildStep#deprecated","started":"20:24:26.043","dependents":[303],"id":73,"thread":"build-31"},{"duration":9,"stepId":"io.quarkus.arc.deployment.ArcProcessor#registerSyntheticObservers","started":"20:24:26.824","dependents":[352,325,301,313,309],"id":300,"thread":"build-20"},{"duration":9,"stepId":"io.quarkus.smallrye.context.deployment.SmallRyeContextPropagationProcessor#build","started":"20:24:26.307","dependents":[353,299,296,298],"id":205,"thread":"build-5"},{"duration":9,"stepId":"io.quarkus.narayana.jta.deployment.NarayanaJtaProcessor#registerScope","started":"20:24:26.043","dependents":[69],"id":66,"thread":"build-21"},{"duration":9,"stepId":"io.quarkus.hibernate.orm.panache.deployment.PanacheHibernateResourceProcessor#ensureBeanLookupAvailable","started":"20:24:26.027","dependents":[313,309],"id":38,"thread":"build-40"},{"duration":9,"stepId":"io.quarkus.deployment.dev.testing.TestTracingProcessor#startTesting","started":"20:24:26.402","dependents":[349,350,276,348],"id":216,"thread":"build-5"},{"duration":9,"stepId":"io.quarkus.vertx.deployment.VertxProcessor#registerBean","started":"20:24:26.032","dependents":[284,269],"id":49,"thread":"build-8"},{"duration":9,"stepId":"io.quarkus.deployment.logging.LoggingResourceProcessor#setUpDefaultLevels","started":"20:24:26.054","dependents":[276,319],"id":107,"thread":"build-62"},{"duration":8,"stepId":"io.quarkus.deployment.steps.ConfigGenerationBuildStep#staticInitSources","started":"20:24:25.975","dependents":[341],"id":4,"thread":"build-2"},{"duration":8,"stepId":"io.quarkus.hibernate.orm.panache.deployment.PanacheHibernateResourceProcessor#produceModel","started":"20:24:26.023","dependents":[243,342],"id":26,"thread":"build-16"},{"duration":8,"stepId":"io.quarkus.deployment.steps.CombinedIndexBuildStep#build","started":"20:24:26.464","dependents":[241,223,236,263,224,287,235,233,240,229,244,225,284,274,226,257,255,227,343,242,316,315,288,265,243,283,276,238,228,231,251,335,280,239,248,282,252,230,247,250,232,234,246,344,279],"id":222,"thread":"build-51"},{"duration":8,"stepId":"io.quarkus.narayana.jta.deployment.NarayanaJtaProcessor#logCleanupFilters","started":"20:24:25.982","dependents":[145,276],"id":8,"thread":"build-8"},{"duration":7,"stepId":"io.quarkus.vertx.http.deployment.devmode.console.DevConsoleProcessor#setupWebJar","started":"20:24:25.979","dependents":[277],"id":3,"thread":"build-5"},{"duration":7,"stepId":"io.quarkus.vertx.http.deployment.VertxHttpProcessor#finalizeRouter","started":"20:24:27.022","dependents":[353,349,340,350,348],"id":339,"thread":"build-17"},{"duration":7,"stepId":"io.quarkus.hibernate.orm.deployment.HibernateOrmProcessor#devServicesAutoGenerateByDefault","started":"20:24:26.515","dependents":[303],"id":267,"thread":"build-45"},{"duration":6,"stepId":"io.quarkus.deployment.CollectionClassProcessor#setupCollectionClasses","started":"20:24:25.976","dependents":[352],"id":1,"thread":"build-4"},{"duration":6,"stepId":"io.quarkus.deployment.steps.MainClassBuildStep#applicationReflection","started":"20:24:26.037","dependents":[352],"id":53,"thread":"build-46"},{"duration":6,"stepId":"io.quarkus.resteasy.jackson.deployment.ResteasyJacksonProcessor#feature","started":"20:24:25.981","dependents":[353],"id":7,"thread":"build-7"},{"duration":6,"stepId":"io.quarkus.datasource.deployment.devservices.DevUIDatasourceProcessor#devConsoleInfo","started":"20:24:26.056","dependents":[323],"id":94,"thread":"build-21"},{"duration":6,"stepId":"io.quarkus.netty.deployment.NettyProcessor#cleanupMacDNSInLog","started":"20:24:26.033","dependents":[145,276],"id":44,"thread":"build-34"},{"duration":5,"stepId":"io.quarkus.arc.deployment.ArcProcessor#loggerProducer","started":"20:24:26.047","dependents":[284,269],"id":70,"thread":"build-8"},{"duration":5,"stepId":"io.quarkus.arc.deployment.ConfigBuildStep#vetoMPConfigProperties","started":"20:24:25.984","dependents":[284],"id":6,"thread":"build-10"},{"duration":5,"stepId":"io.quarkus.deployment.steps.RegisterForReflectionBuildStep#build","started":"20:24:26.473","dependents":[352,283],"id":248,"thread":"build-53"},{"duration":5,"stepId":"io.quarkus.devservices.deployment.DevServicesProcessor#config","started":"20:24:26.853","dependents":[306,308],"id":305,"thread":"build-5"},{"duration":5,"stepId":"io.quarkus.deployment.logging.LoggingResourceProcessor#setupStackTraceFormatter","started":"20:24:26.464","dependents":[276],"id":221,"thread":"build-5"},{"duration":5,"stepId":"io.quarkus.hibernate.orm.deployment.HibernateOrmProcessor#addPersistenceUnitAnnotationToIndex","started":"20:24:26.020","dependents":[222],"id":22,"thread":"build-37"},{"duration":4,"stepId":"io.quarkus.panache.common.deployment.PanacheHibernateCommonResourceProcessor#findEntityClasses","started":"20:24:26.515","dependents":[343],"id":265,"thread":"build-57"},{"duration":4,"stepId":"io.quarkus.vertx.http.deployment.devmode.console.DevConsoleProcessor#builder","started":"20:24:26.243","dependents":[347,324],"id":163,"thread":"build-1"},{"duration":4,"stepId":"io.quarkus.arc.deployment.BuildTimeEnabledProcessor#unlessBuildProperty","started":"20:24:26.473","dependents":[245,280],"id":244,"thread":"build-3"},{"duration":4,"stepId":"io.quarkus.vertx.deployment.VertxProcessor#registerVerticleClasses","started":"20:24:26.473","dependents":[352],"id":240,"thread":"build-56"},{"duration":4,"stepId":"io.quarkus.arc.deployment.ConfigBuildStep#registerConfigClasses","started":"20:24:26.872","dependents":[353],"id":320,"thread":"build-11"},{"duration":4,"stepId":"io.quarkus.deployment.index.ApplicationArchiveBuildStep#addConfiguredIndexedDependencies","started":"20:24:26.059","dependents":[217],"id":101,"thread":"build-36"},{"duration":4,"stepId":"io.quarkus.deployment.steps.CurateOutcomeBuildStep#curateOutcome","started":"20:24:26.059","dependents":[347,111,110,302,191,159,307,138,239,174,144,114,217,345,277,323,324,135],"id":109,"thread":"build-53"},{"duration":4,"stepId":"io.quarkus.arc.deployment.SplitPackageProcessor#splitPackageDetection","started":"20:24:26.464","dependents":[325],"id":220,"thread":"build-57"},{"duration":4,"stepId":"io.quarkus.jackson.deployment.JacksonProcessor#jacksonSupport","started":"20:24:26.473","dependents":[353,299,296,298],"id":247,"thread":"build-45"},{"duration":4,"stepId":"io.quarkus.deployment.steps.CapabilityAggregationStep#provideCapabilities","started":"20:24:26.064","dependents":[114],"id":111,"thread":"build-7"},{"duration":4,"stepId":"io.quarkus.arc.deployment.BuildTimeEnabledProcessor#ifBuildProperty","started":"20:24:26.473","dependents":[245,280],"id":242,"thread":"build-57"},{"duration":4,"stepId":"io.quarkus.vertx.core.deployment.VertxCoreProcessor#registerVerticleClasses","started":"20:24:26.472","dependents":[352],"id":241,"thread":"build-5"},{"duration":4,"stepId":"io.quarkus.deployment.steps.MainClassBuildStep#mainClassBuildStep","started":"20:24:26.473","dependents":[],"id":246,"thread":"build-24"},{"duration":4,"stepId":"io.quarkus.deployment.steps.ApplicationInfoBuildStep#create","started":"20:24:26.057","dependents":[353],"id":92,"thread":"build-63"},{"duration":4,"stepId":"io.quarkus.hibernate.orm.deployment.HibernateOrmProcessor#jpaEntitiesIndexer","started":"20:24:26.473","dependents":[253,346],"id":243,"thread":"build-28"},{"duration":4,"stepId":"io.quarkus.deployment.steps.BlockingOperationControlBuildStep#blockingOP","started":"20:24:26.289","dependents":[353],"id":200,"thread":"build-4"},{"duration":4,"stepId":"io.quarkus.deployment.pkg.steps.PackageTypeVerificationBuildStep#builtins","started":"20:24:26.021","dependents":[112],"id":21,"thread":"build-8"},{"duration":3,"stepId":"io.quarkus.arc.deployment.SyntheticBeansProcessor#initStatic","started":"20:24:26.811","dependents":[353,300],"id":296,"thread":"build-6"},{"duration":3,"stepId":"io.quarkus.hibernate.orm.panache.common.deployment.PanacheJpaCommonResourceProcessor#lookupNamedQueries_5a86a91ed8ef1aa483288c8239df231983eeb766","started":"20:24:26.514","dependents":[266],"id":263,"thread":"build-12"},{"duration":3,"stepId":"io.quarkus.resteasy.server.common.deployment.ResteasyServerCommonProcessor#beanDefiningAnnotations","started":"20:24:26.056","dependents":[144,284,269],"id":90,"thread":"build-49"},{"duration":3,"stepId":"io.quarkus.jackson.deployment.JacksonProcessor#register","started":"20:24:26.473","dependents":[352,284,283,269],"id":239,"thread":"build-2"},{"duration":3,"stepId":"io.quarkus.arc.deployment.HotDeploymentConfigBuildStep#startup","started":"20:24:25.986","dependents":[16],"id":5,"thread":"build-13"},{"duration":3,"stepId":"io.quarkus.resteasy.deployment.ResteasyStandaloneBuildStep#boot","started":"20:24:27.017","dependents":[353,339,347,338,336],"id":335,"thread":"build-17"},{"duration":3,"stepId":"io.quarkus.deployment.steps.ReflectiveHierarchyStep#build","started":"20:24:26.635","dependents":[352],"id":283,"thread":"build-20"},{"duration":3,"stepId":"io.quarkus.agroal.deployment.AgroalProcessor#generateDataSourceBeans","started":"20:24:26.395","dependents":[353,299,213,296,260,298,255,328],"id":212,"thread":"build-5"},{"duration":3,"stepId":"io.quarkus.deployment.steps.DevServicesConfigBuildStep#setup","started":"20:24:26.850","dependents":[349,304,350,305,319,307,348],"id":303,"thread":"build-45"},{"duration":3,"stepId":"io.quarkus.deployment.pkg.steps.FileSystemResourcesBuildStep#notNormalMode","started":"20:24:26.100","dependents":[],"id":134,"thread":"build-22"},{"duration":3,"stepId":"io.quarkus.hibernate.orm.deployment.HibernateOrmProcessor#registerHibernateOrmMetadataForCoreDialects","started":"20:24:26.016","dependents":[255],"id":20,"thread":"build-34"},{"duration":3,"stepId":"io.quarkus.arc.deployment.staticmethods.InterceptedStaticMethodsProcessor#collectInterceptedStaticMethods","started":"20:24:26.810","dependents":[295,329,313,309],"id":294,"thread":"build-49"},{"duration":3,"stepId":"io.quarkus.hibernate.orm.deployment.HibernateOrmProcessor#hotDeploymentWatchedFiles","started":"20:24:26.049","dependents":[268],"id":65,"thread":"build-62"},{"duration":2,"stepId":"io.quarkus.deployment.console.ConsoleProcessor#setupExceptionHandler","started":"20:24:26.402","dependents":[221],"id":215,"thread":"build-57"},{"duration":2,"stepId":"io.quarkus.deployment.steps.NativeImageFeatureStep#generateNativeResourcesList","started":"20:24:26.515","dependents":[],"id":264,"thread":"build-28"},{"duration":2,"stepId":"io.quarkus.jackson.deployment.JacksonProcessor#supportMixins","started":"20:24:26.473","dependents":[353,299,352,296,298],"id":238,"thread":"build-17"},{"duration":2,"stepId":"io.quarkus.arc.deployment.ConfigBuildStep#registerConfigMappingConverters","started":"20:24:26.472","dependents":[352],"id":236,"thread":"build-38"},{"duration":2,"stepId":"io.quarkus.arc.deployment.ReflectiveBeanClassesProcessor#implicitReflectiveBeanClasses","started":"20:24:26.810","dependents":[325],"id":292,"thread":"build-5"},{"duration":2,"stepId":"io.quarkus.vertx.deployment.VertxProcessor#collectEventConsumers","started":"20:24:26.810","dependents":[297,300],"id":293,"thread":"build-56"},{"duration":2,"stepId":"io.quarkus.deployment.steps.ConfigGenerationBuildStep#builderMappings","started":"20:24:26.872","dependents":[352,341],"id":317,"thread":"build-24"},{"duration":2,"stepId":"io.quarkus.narayana.jta.deployment.NarayanaJtaProcessor#transactionContext","started":"20:24:26.662","dependents":[286],"id":285,"thread":"build-20"},{"duration":2,"stepId":"io.quarkus.undertow.deployment.UndertowStaticResourcesBuildStep#handleGeneratedWebResources","started":"20:24:26.070","dependents":[],"id":119,"thread":"build-2"},{"duration":2,"stepId":"io.quarkus.hibernate.orm.deployment.HibernateOrmProcessor#enforceDisableRuntimeEnhancer","started":"20:24:25.999","dependents":[353],"id":17,"thread":"build-29"},{"duration":2,"stepId":"io.quarkus.vertx.deployment.VertxProcessor#featureAndCapability","started":"20:24:26.032","dependents":[353,114],"id":35,"thread":"build-24"},{"duration":2,"stepId":"io.quarkus.arc.deployment.ConfigBuildStep#warnStaticInitInjectionPoints","started":"20:24:26.872","dependents":[319],"id":316,"thread":"build-6"},{"duration":2,"stepId":"io.quarkus.hibernate.orm.panache.deployment.PanacheHibernateResourceProcessor#build","started":"20:24:27.276","dependents":[353,345],"id":344,"thread":"build-50"},{"duration":2,"stepId":"io.quarkus.hibernate.orm.panache.common.deployment.PanacheJpaCommonResourceProcessor#buildNamedQueryMap","started":"20:24:26.518","dependents":[353],"id":266,"thread":"build-56"},{"duration":2,"stepId":"io.quarkus.deployment.recording.AnnotationProxyBuildStep#build","started":"20:24:26.284","dependents":[297],"id":194,"thread":"build-49"},{"duration":2,"stepId":"io.quarkus.vertx.http.deployment.devmode.console.ConfigEditorProcessor#handleRequests","started":"20:24:26.853","dependents":[347,324],"id":304,"thread":"build-12"},{"duration":2,"stepId":"io.quarkus.arc.deployment.AutoAddScopeProcessor#annotationTransformer","started":"20:24:26.559","dependents":[284,313,309],"id":275,"thread":"build-12"},{"duration":2,"stepId":"io.quarkus.hibernate.orm.deployment.HibernateOrmCdiProcessor#validatePersistenceUnitExtensions","started":"20:24:26.872","dependents":[325],"id":318,"thread":"build-56"},{"duration":2,"stepId":"io.quarkus.resteasy.common.deployment.ResteasyCommonProcessor#resteasyConfig","started":"20:24:26.070","dependents":[279],"id":120,"thread":"build-35"},{"duration":2,"stepId":"io.quarkus.vertx.deployment.VertxProcessor#build","started":"20:24:26.812","dependents":[353,352,349,350,348],"id":297,"thread":"build-5"},{"duration":2,"stepId":"io.quarkus.hibernate.orm.deployment.HibernateOrmProcessor#pregenProxies","started":"20:24:27.334","dependents":[353],"id":346,"thread":"build-25"},{"duration":1,"stepId":"io.quarkus.deployment.steps.ReflectiveHierarchyStep#ignoreJavaClassWarnings","started":"20:24:25.983","dependents":[283],"id":2,"thread":"build-9"},{"duration":1,"stepId":"io.quarkus.deployment.steps.NativeImageResourcesStep#registerPackageResources","started":"20:24:26.047","dependents":[264],"id":63,"thread":"build-36"},{"duration":1,"stepId":"io.quarkus.deployment.JniProcessor#setupJni","started":"20:24:26.054","dependents":[170],"id":81,"thread":"build-5"},{"duration":1,"stepId":"io.quarkus.deployment.steps.ConfigGenerationBuildStep#runtimeDefaultsConfig","started":"20:24:26.875","dependents":[352,341],"id":319,"thread":"build-5"},{"duration":1,"stepId":"io.quarkus.vertx.core.deployment.VertxCoreProcessor#cleanupVertxWarnings","started":"20:24:25.993","dependents":[145,276],"id":15,"thread":"build-23"},{"duration":1,"stepId":"io.quarkus.hibernate.orm.deployment.HibernateOrmCdiProcessor#convertJpaResourceAnnotationsToQualifier","started":"20:24:26.515","dependents":[284],"id":262,"thread":"build-56"},{"duration":1,"stepId":"io.quarkus.smallrye.context.deployment.SmallRyeContextPropagationProcessor#createSynthBeansForConfiguredInjectionPoints","started":"20:24:26.810","dependents":[353,299,296,298],"id":291,"thread":"build-57"},{"duration":1,"stepId":"io.quarkus.jdbc.h2.deployment.JDBCH2Processor#registerDriver","started":"20:24:26.055","dependents":[159],"id":87,"thread":"build-36"},{"duration":1,"stepId":"io.quarkus.deployment.logging.LoggingResourceProcessor#setUpDarkeningDefault","started":"20:24:25.990","dependents":[319],"id":12,"thread":"build-18"},{"duration":1,"stepId":"io.quarkus.deployment.steps.ShutdownListenerBuildStep#setupShutdown","started":"20:24:27.030","dependents":[353],"id":340,"thread":"build-50"},{"duration":1,"stepId":"io.quarkus.vertx.deployment.EventBusCodecProcessor#registerCodecs","started":"20:24:26.559","dependents":[297,352],"id":274,"thread":"build-56"},{"duration":1,"stepId":"io.quarkus.deployment.dev.ConfigureDisableInstrumentationBuildStep#configure","started":"20:24:25.997","dependents":[349,350,348],"id":16,"thread":"build-24"},{"duration":1,"stepId":"io.quarkus.mutiny.deployment.MutinyProcessor#runtimeInit","started":"20:24:26.307","dependents":[353],"id":203,"thread":"build-4"},{"duration":1,"stepId":"io.quarkus.resteasy.deployment.ResteasyServletProcessor#addServletsToExceptionMapper","started":"20:24:27.017","dependents":[353],"id":334,"thread":"build-11"},{"duration":1,"stepId":"io.quarkus.arc.deployment.StartupBuildSteps#registerStartupObservers","started":"20:24:26.834","dependents":[309],"id":301,"thread":"build-45"},{"duration":1,"stepId":"io.quarkus.deployment.steps.CapabilityAggregationStep#aggregateCapabilities","started":"20:24:26.068","dependents":[261,175,218,128,284,331,181,115,237,257,255,116,183,213,120,118,199,248,282,219,333,137,250,234,119,117,279,212],"id":114,"thread":"build-29"},{"duration":1,"stepId":"io.quarkus.hibernate.orm.panache.deployment.PanacheHibernateResourceProcessor#marker","started":"20:24:25.990","dependents":[217],"id":11,"thread":"build-19"},{"duration":1,"stepId":"io.quarkus.deployment.logging.LoggingResourceProcessor#setupLogFilters","started":"20:24:26.039","dependents":[145,276],"id":45,"thread":"build-51"},{"duration":1,"stepId":"io.quarkus.deployment.SslProcessor#setupNativeSsl","started":"20:24:26.054","dependents":[87,170,199,212],"id":80,"thread":"build-33"},{"duration":1,"stepId":"io.quarkus.hibernate.orm.deployment.HibernateOrmProcessor#checkTransactionsSupport","started":"20:24:26.070","dependents":[325],"id":118,"thread":"build-27"},{"duration":1,"stepId":"io.quarkus.resteasy.common.deployment.ResteasyCommonProcessor#setupGzipProviders","started":"20:24:26.058","dependents":[279],"id":88,"thread":"build-64"},{"duration":1,"stepId":"io.quarkus.arc.deployment.StartupBuildSteps#unremovableBeans","started":"20:24:26.035","dependents":[313,309],"id":36,"thread":"build-47"},{"duration":1,"stepId":"io.quarkus.resteasy.server.common.deployment.ResteasyServerCommonProcessor#registerCompatibleAnnotationPrefixes","started":"20:24:26.054","dependents":[280],"id":84,"thread":"build-55"},{"duration":1,"stepId":"io.quarkus.hibernate.orm.panache.deployment.PanacheHibernateResourceProcessor#featureBuildItem","started":"20:24:26.030","dependents":[353],"id":27,"thread":"build-8"},{"duration":1,"stepId":"io.quarkus.jdbc.h2.deployment.JDBCH2Processor#feature","started":"20:24:26.047","dependents":[353],"id":62,"thread":"build-46"},{"duration":1,"stepId":"io.quarkus.arc.deployment.ArcProcessor#setupExecutor","started":"20:24:26.307","dependents":[353],"id":204,"thread":"build-37"},{"duration":1,"stepId":"io.quarkus.panache.common.deployment.PanacheHibernateCommonResourceProcessor#replaceFieldAccesses","started":"20:24:27.276","dependents":[345],"id":343,"thread":"build-56"},{"duration":1,"stepId":"io.quarkus.hibernate.orm.deployment.HibernateOrmAlwaysEnabledProcessor#featureBuildItem","started":"20:24:25.989","dependents":[353],"id":9,"thread":"build-16"},{"duration":1,"stepId":"io.quarkus.netty.deployment.NettyProcessor#registerEventLoopBeans","started":"20:24:26.319","dependents":[353,299,296,298],"id":208,"thread":"build-30"},{"duration":1,"stepId":"io.quarkus.vertx.http.deployment.StaticResourcesProcessor#runtimeInit","started":"20:24:27.015","dependents":[353,339],"id":332,"thread":"build-12"},{"duration":1,"stepId":"io.quarkus.vertx.http.deployment.devmode.console.DevConsoleProcessor#buildTimeTemplates","started":"20:24:26.896","dependents":[349,350,348],"id":323,"thread":"build-45"},{"duration":1,"stepId":"io.quarkus.vertx.http.deployment.VertxHttpProcessor#initializeRouter","started":"20:24:27.020","dependents":[353,339],"id":338,"thread":"build-50"},{"duration":1,"stepId":"io.quarkus.resteasy.common.deployment.ResteasyCommonProcessor#setupResteasyInjection","started":"20:24:27.015","dependents":[353,333,331],"id":330,"thread":"build-11"},{"duration":0,"stepId":"io.quarkus.hibernate.orm.deployment.HibernateOrmCdiProcessor#generateDataSourceBeans","started":"20:24:26.515","dependents":[353,299,296,284,269,298],"id":260,"thread":"build-24"},{"duration":0,"stepId":"io.quarkus.deployment.steps.ConfigGenerationBuildStep#suppressNonRuntimeConfigChanged","started":"20:24:26.036","dependents":[180],"id":40,"thread":"build-24"},{"duration":0,"stepId":"io.quarkus.arc.deployment.devconsole.ArcDevConsoleProcessor#monitor","started":"20:24:26.143","dependents":[349,284,269],"id":144,"thread":"build-6"},{"duration":0,"stepId":"io.quarkus.undertow.deployment.UndertowStaticResourcesBuildStep#scanStaticResources","started":"20:24:26.464","dependents":[219],"id":218,"thread":"build-17"},{"duration":0,"stepId":"io.quarkus.hibernate.orm.deployment.HibernateOrmProcessor#registerBeans","started":"20:24:26.515","dependents":[284,269,313,309],"id":257,"thread":"build-3"},{"duration":0,"stepId":"io.quarkus.deployment.console.ConsoleProcessor#installCliCommands","started":"20:24:26.869","dependents":[349,350,348],"id":308,"thread":"build-12"},{"duration":0,"stepId":"io.quarkus.resteasy.common.deployment.ResteasyCommonProcessor#addStaticInitConfigSourceProvider","started":"20:24:26.070","dependents":[352,341],"id":115,"thread":"build-23"},{"duration":0,"stepId":"io.quarkus.resteasy.deployment.ResteasyServletProcessor#webXmlMapping","started":"20:24:26.035","dependents":[280],"id":34,"thread":"build-46"},{"duration":0,"stepId":"io.quarkus.hibernate.orm.deployment.HibernateOrmProcessor#startPersistenceUnits","started":"20:24:27.015","dependents":[353,349,350,348],"id":328,"thread":"build-17"},{"duration":0,"stepId":"io.quarkus.resteasy.common.deployment.ResteasyCommonProcessor#configInjectionStaticInitProvider","started":"20:24:26.055","dependents":[316],"id":82,"thread":"build-49"},{"duration":0,"stepId":"io.quarkus.hibernate.orm.deployment.HibernateOrmProcessor#build_7a4403d699506d83ac39616f3c11e5e1b448d863","started":"20:24:26.515","dependents":[353,325],"id":261,"thread":"build-6"},{"duration":0,"stepId":"io.quarkus.deployment.steps.CurateOutcomeBuildStep#removeResources","started":"20:24:26.064","dependents":[345],"id":110,"thread":"build-29"},{"duration":0,"stepId":"io.quarkus.arc.deployment.ConfigBuildStep#validateConfigMappingsInjectionPoints","started":"20:24:26.872","dependents":[320,317,341],"id":313,"thread":"build-28"},{"duration":0,"stepId":"io.quarkus.hibernate.orm.deployment.HibernateOrmProcessor#defineTypeOfImpliedPU","started":"20:24:26.398","dependents":[260,255,262],"id":213,"thread":"build-57"},{"duration":0,"stepId":"io.quarkus.arc.deployment.TestsAsBeansProcessor#testAnnotations","started":"20:24:26.047","dependents":[144,284,269],"id":60,"thread":"build-58"},{"duration":0,"stepId":"io.quarkus.deployment.ide.IdeProcessor#effectiveIde","started":"20:24:26.243","dependents":[221,163,347,215],"id":162,"thread":"build-40"},{"duration":0,"stepId":"io.quarkus.deployment.steps.AdditionalClassLoaderResourcesBuildStep#appendAdditionalClassloaderResources","started":"20:24:26.043","dependents":[222],"id":55,"thread":"build-8"},{"duration":0,"stepId":"io.quarkus.hibernate.orm.deployment.HibernateOrmProcessor#candidatesForFieldAccess","started":"20:24:26.514","dependents":[265],"id":254,"thread":"build-49"},{"duration":0,"stepId":"io.quarkus.arc.deployment.staticmethods.InterceptedStaticMethodsProcessor#callInitializer","started":"20:24:27.015","dependents":[353],"id":329,"thread":"build-50"},{"duration":0,"stepId":"io.quarkus.netty.deployment.NettyProcessor#limitArenaSize","started":"20:24:26.062","dependents":[353],"id":93,"thread":"build-68"},{"duration":0,"stepId":"io.quarkus.arc.deployment.ArcProcessor#validateAsyncObserverExceptionHandlers","started":"20:24:26.872","dependents":[325],"id":312,"thread":"build-11"},{"duration":0,"stepId":"io.quarkus.arc.deployment.TestsAsBeansProcessor#testClassBeans","started":"20:24:26.043","dependents":[284,269],"id":54,"thread":"build-56"},{"duration":0,"stepId":"io.quarkus.arc.deployment.ArcProcessor#quarkusApplication","started":"20:24:26.473","dependents":[284,269],"id":233,"thread":"build-4"},{"duration":0,"stepId":"io.quarkus.deployment.steps.PreloadClassesBuildStep#registerPreInitClasses","started":"20:24:26.032","dependents":[],"id":28,"thread":"build-34"},{"duration":0,"stepId":"io.quarkus.deployment.logging.LoggingResourceProcessor#setProperty","started":"20:24:25.993","dependents":[353],"id":13,"thread":"build-20"},{"duration":0,"stepId":"io.quarkus.hibernate.orm.deployment.HibernateOrmProcessor#contributePersistenceXmlToJpaModel","started":"20:24:26.233","dependents":[253],"id":157,"thread":"build-58"},{"duration":0,"stepId":"io.quarkus.resteasy.common.deployment.ResteasyCommonProcessor#disableDefaultExceptionMapper","started":"20:24:26.055","dependents":[353],"id":85,"thread":"build-53"},{"duration":0,"stepId":"io.quarkus.jdbc.h2.deployment.H2JDBCReflections#build","started":"20:24:26.036","dependents":[352],"id":39,"thread":"build-49"},{"duration":0,"stepId":"io.quarkus.arc.deployment.AutoInjectFieldProcessor#autoInjectQualifiers","started":"20:24:26.559","dependents":[273,275,280],"id":270,"thread":"build-49"},{"duration":0,"stepId":"io.quarkus.deployment.steps.BannerProcessor#watchBannerChanges","started":"20:24:26.057","dependents":[268],"id":86,"thread":"build-53"},{"duration":0,"stepId":"io.quarkus.vertx.http.deployment.devmode.console.DevConsoleProcessor#setupDevConsoleRoutes_8bb86a3e770caadb970f4facb490e30df7a2a187","started":"20:24:26.601","dependents":[353,347,338,336],"id":278,"thread":"build-11"},{"duration":0,"stepId":"io.quarkus.arc.deployment.ArcProcessor#exposeCustomScopeNames","started":"20:24:26.052","dependents":[144,290,284,272,269,232,275,131,280],"id":69,"thread":"build-62"},{"duration":0,"stepId":"io.quarkus.hibernate.orm.deployment.HibernateOrmProcessor#produceLoggingCategories","started":"20:24:26.054","dependents":[107],"id":78,"thread":"build-5"},{"duration":0,"stepId":"io.quarkus.resteasy.server.common.deployment.ResteasyServerCommonProcessor#processPathInterfaceImplementors","started":"20:24:26.473","dependents":[284,269,313,309],"id":232,"thread":"build-41"},{"duration":0,"stepId":"io.quarkus.hibernate.orm.deployment.HibernateOrmProcessor#multitenancy","started":"20:24:26.515","dependents":[353,299,296,298,313,309],"id":256,"thread":"build-53"},{"duration":0,"stepId":"io.quarkus.arc.deployment.BuildTimeEnabledProcessor#ifBuildProfile","started":"20:24:26.472","dependents":[245,280],"id":223,"thread":"build-57"},{"duration":0,"stepId":"io.quarkus.deployment.dev.testing.TestTracingProcessor#handle","started":"20:24:26.047","dependents":[145,276],"id":59,"thread":"build-60"},{"duration":0,"stepId":"io.quarkus.arc.deployment.WrongAnnotationUsageProcessor#detect","started":"20:24:26.810","dependents":[325],"id":290,"thread":"build-45"},{"duration":0,"stepId":"io.quarkus.undertow.deployment.UndertowStaticResourcesBuildStep#nativeImageResources","started":"20:24:26.464","dependents":[264],"id":219,"thread":"build-38"},{"duration":0,"stepId":"io.quarkus.deployment.logging.LoggingWithPanacheProcessor#process","started":"20:24:26.473","dependents":[345],"id":225,"thread":"build-49"},{"duration":0,"stepId":"io.quarkus.arc.deployment.ConfigBuildStep#registerCustomConfigBeanTypes","started":"20:24:26.810","dependents":[299,352,296,298],"id":289,"thread":"build-6"},{"duration":0,"stepId":"io.quarkus.vertx.http.deployment.devmode.console.DevConsoleProcessor#setupDevConsoleWebjar","started":"20:24:26.047","dependents":[277],"id":61,"thread":"build-61"},{"duration":0,"stepId":"io.quarkus.arc.deployment.BuildTimeEnabledProcessor#conditionTransformer","started":"20:24:26.477","dependents":[284],"id":245,"thread":"build-28"},{"duration":0,"stepId":"io.quarkus.vertx.http.deployment.devmode.console.DevConsoleProcessor#config","started":"20:24:26.858","dependents":[323],"id":306,"thread":"build-12"},{"duration":0,"stepId":"io.quarkus.vertx.http.deployment.devmode.console.DevConsoleProcessor#runtimeTemplates","started":"20:24:27.860","dependents":[353],"id":349,"thread":"build-25"},{"duration":0,"stepId":"io.quarkus.resteasy.server.common.deployment.ResteasyLogFilterBuildStep#setupLogFilters","started":"20:24:26.041","dependents":[145,276],"id":47,"thread":"build-53"},{"duration":0,"stepId":"io.quarkus.arc.deployment.ConfigBuildStep#registerConfigMappingsBean","started":"20:24:26.810","dependents":[300],"id":288,"thread":"build-20"},{"duration":0,"stepId":"io.quarkus.deployment.steps.ConfigGenerationBuildStep#extensionMappings","started":"20:24:26.473","dependents":[310,352,316,288,287,313],"id":231,"thread":"build-55"},{"duration":0,"stepId":"io.quarkus.resteasy.deployment.RestPathAnnotationProcessor#findRestPaths","started":"20:24:26.635","dependents":[284],"id":282,"thread":"build-11"},{"duration":0,"stepId":"io.quarkus.arc.deployment.ConfigBuildStep#validateConfigInjectionPoints","started":"20:24:26.872","dependents":[327],"id":311,"thread":"build-3"},{"duration":0,"stepId":"io.quarkus.vertx.core.deployment.VertxCoreProcessor#preventLoggerContention","started":"20:24:26.038","dependents":[107],"id":43,"thread":"build-22"},{"duration":0,"stepId":"io.quarkus.hibernate.orm.deployment.HibernateOrmProcessor#configurationDescriptorBuilding","started":"20:24:26.514","dependents":[261,256,353,267,268,346,260,258,257,259,262,264],"id":255,"thread":"build-18"},{"duration":0,"stepId":"io.quarkus.deployment.ForkJoinPoolProcessor#setProperty","started":"20:24:26.035","dependents":[353],"id":33,"thread":"build-28"},{"duration":0,"stepId":"io.quarkus.arc.deployment.ObserverValidationProcessor#validateApplicationObserver","started":"20:24:26.872","dependents":[325],"id":314,"thread":"build-24"},{"duration":0,"stepId":"io.quarkus.arc.deployment.ConfigBuildStep#validateConfigPropertiesInjectionPoints","started":"20:24:26.872","dependents":[320],"id":310,"thread":"build-12"},{"duration":0,"stepId":"io.quarkus.agroal.deployment.AgroalProcessor#agroal","started":"20:24:26.041","dependents":[353],"id":50,"thread":"build-31"},{"duration":0,"stepId":"io.quarkus.arc.deployment.HotDeploymentConfigBuildStep#configFile","started":"20:24:26.047","dependents":[268],"id":58,"thread":"build-27"},{"duration":0,"stepId":"io.quarkus.arc.deployment.BuildTimeEnabledProcessor#unlessBuildProfile","started":"20:24:26.473","dependents":[245,280],"id":228,"thread":"build-65"},{"duration":0,"stepId":"io.quarkus.hibernate.orm.deployment.HibernateOrmProcessor#build_daeea4f2c9416db083cc1423ec1bf5c757ad2a16","started":"20:24:26.515","dependents":[353,344],"id":258,"thread":"build-28"},{"duration":0,"stepId":"io.quarkus.arc.deployment.ConfigBuildStep#validateConfigValues","started":"20:24:27.015","dependents":[353,352],"id":327,"thread":"build-3"},{"duration":0,"stepId":"io.quarkus.arc.deployment.AutoProducerMethodsProcessor#annotationTransformer","started":"20:24:26.559","dependents":[284],"id":272,"thread":"build-45"},{"duration":0,"stepId":"io.quarkus.vertx.http.deployment.VertxHttpProcessor#notFoundRoutes","started":"20:24:27.020","dependents":[337],"id":336,"thread":"build-12"},{"duration":0,"stepId":"io.quarkus.deployment.steps.RuntimeConfigSetupBuildStep#setupRuntimeConfig","started":"20:24:26.182","dependents":[179,338,202,190,350,276,258,180,173,351,207,335,210,353,339,340,332,181,209,192,172,211,206,212],"id":151,"thread":"build-62"},{"duration":0,"stepId":"io.quarkus.resteasy.deployment.ResteasyStandaloneBuildStep#staticInit","started":"20:24:27.017","dependents":[353,335],"id":333,"thread":"build-50"},{"duration":0,"stepId":"io.quarkus.arc.deployment.ArcProcessor#feature","started":"20:24:26.042","dependents":[353],"id":52,"thread":"build-56"},{"duration":0,"stepId":"io.quarkus.hibernate.orm.deployment.HibernateOrmProcessor#enrollBeanValidationTypeSafeActivatorForReflection","started":"20:24:26.070","dependents":[352],"id":117,"thread":"build-16"},{"duration":0,"stepId":"io.quarkus.arc.deployment.LookupConditionsProcessor#suppressConditionsGenerators","started":"20:24:26.559","dependents":[284],"id":271,"thread":"build-57"},{"duration":0,"stepId":"io.quarkus.jackson.deployment.JacksonProcessor#autoRegisterModules","started":"20:24:26.473","dependents":[251],"id":235,"thread":"build-37"},{"duration":0,"stepId":"io.quarkus.hibernate.orm.panache.deployment.PanacheHibernateResourceProcessor#collectEntityClasses","started":"20:24:26.473","dependents":[344],"id":226,"thread":"build-24"},{"duration":0,"stepId":"io.quarkus.resteasy.deployment.ResteasyBuiltinsProcessor#addAdditionalEndpointsExceptionMapper","started":"20:24:27.020","dependents":[353],"id":337,"thread":"build-17"},{"duration":0,"stepId":"io.quarkus.resteasy.deployment.ResteasyServletProcessor#build","started":"20:24:27.017","dependents":[353,352,334],"id":331,"thread":"build-17"},{"duration":0,"stepId":"io.quarkus.resteasy.deployment.ResteasyServletProcessor#jaxrsConfig","started":"20:24:26.635","dependents":[282],"id":281,"thread":"build-28"},{"duration":0,"stepId":"io.quarkus.arc.deployment.LifecycleEventsBuildStep#startupEvent","started":"20:24:27.860","dependents":[353,351],"id":350,"thread":"build-56"},{"duration":0,"stepId":"io.quarkus.hibernate.orm.deployment.HibernateOrmProcessor#includeArchivesHostingEntityPackagesInIndex","started":"20:24:26.055","dependents":[217],"id":83,"thread":"build-21"},{"duration":0,"stepId":"io.quarkus.deployment.ConstructorPropertiesProcessor#build","started":"20:24:26.473","dependents":[352],"id":229,"thread":"build-50"},{"duration":0,"stepId":"io.quarkus.arc.deployment.ConfigBuildStep#registerConfigPropertiesBean","started":"20:24:26.810","dependents":[300],"id":287,"thread":"build-11"},{"duration":0,"stepId":"io.quarkus.resteasy.common.deployment.ResteasyCommonProcessor#registerJsonContextResolvers","started":"20:24:26.473","dependents":[284,269,313,309,279],"id":234,"thread":"build-12"},{"duration":0,"stepId":"io.quarkus.vertx.core.deployment.VertxCoreProcessor#filterNettyHostsFileParsingWarn","started":"20:24:26.030","dependents":[145,276],"id":23,"thread":"build-41"},{"duration":0,"stepId":"io.quarkus.arc.deployment.ConfigBuildStep#generateConfigClasses","started":"20:24:26.473","dependents":[310,352,316,288,287,313],"id":227,"thread":"build-44"},{"duration":0,"stepId":"io.quarkus.arc.deployment.staticmethods.InterceptedStaticMethodsProcessor#processInterceptedStaticMethods","started":"20:24:26.813","dependents":[352,342,345],"id":295,"thread":"build-56"},{"duration":0,"stepId":"io.quarkus.vertx.http.deployment.VertxHttpProcessor#openSocket","started":"20:24:27.861","dependents":[353,352],"id":351,"thread":"build-25"},{"duration":0,"stepId":"io.quarkus.arc.deployment.AutoInjectFieldProcessor#annotationTransformer","started":"20:24:26.559","dependents":[284],"id":273,"thread":"build-5"},{"duration":0,"stepId":"io.quarkus.deployment.ExtensionLoader#booleanSupplierFactory","started":"20:24:26.033","dependents":[111],"id":32,"thread":"build-46"},{"duration":0,"stepId":"io.quarkus.hibernate.orm.panache.deployment.PanacheHibernateResourceProcessor#validate","started":"20:24:26.872","dependents":[325],"id":315,"thread":"build-5"},{"duration":0,"stepId":"io.quarkus.arc.deployment.ArcProcessor#signalBeanContainerReady","started":"20:24:27.014","dependents":[353,339,330,332,350,329,327,328],"id":326,"thread":"build-20"},{"duration":0,"stepId":"io.quarkus.hibernate.orm.deployment.HibernateOrmProcessor#handleNativeImageImportSql","started":"20:24:26.515","dependents":[264],"id":259,"thread":"build-5"},{"duration":0,"stepId":"io.quarkus.hibernate.orm.deployment.HibernateLogFilterBuildStep#setupLogFilters","started":"20:24:25.994","dependents":[145,276],"id":14,"thread":"build-22"},{"duration":0,"stepId":"io.quarkus.hibernate.orm.deployment.HibernateOrmProcessor#warnOfSchemaProblems","started":"20:24:27.860","dependents":[353],"id":348,"thread":"build-38"},{"duration":0,"stepId":"io.quarkus.resteasy.deployment.RestPathAnnotationProcessor#registerBeanClasses","started":"20:24:26.070","dependents":[284,269],"id":116,"thread":"build-7"},{"duration":0,"stepId":"io.quarkus.deployment.steps.ReflectionDiagnosticProcessor#writeReflectionData","started":"20:24:27.861","dependents":[],"id":352,"thread":"build-38"},{"duration":0,"stepId":"io.quarkus.caffeine.deployment.CaffeineProcessor#cacheLoaders","started":"20:24:26.473","dependents":[352],"id":224,"thread":"build-17"},{"duration":0,"stepId":"io.quarkus.hibernate.orm.deployment.HibernateUserTypeProcessor#build","started":"20:24:26.473","dependents":[352],"id":230,"thread":"build-19"}],"started":"2023-04-03T20:24:25.964","buildTarget":"quarkus-crud-sample-v2-1.0.0-SNAPSHOT"}